{
  "annotations": {
    "list": [
      {
        "builtIn": 1,
        "datasource": { "type": "grafana", "uid": "-- Grafana --" },
        "enable": true,
        "hide": true,
        "iconColor": "rgba(0, 211, 255, 1)",
        "name": "Annotations & Alerts",
        "type": "dashboard"
      }
    ]
  },
  "editable": true,
  "fiscalYearStartMonth": 0,
  "graphTooltip": 1,
  "id": null,
  "links": [],
  "panels": [
    {
      "collapsed": false,
      "gridPos": { "h": 1, "w": 24, "x": 0, "y": 0 },
      "id": 100,
      "title": "Availability by Tier",
      "type": "row"
    },
    {
      "datasource": { "type": "prometheus", "uid": "${datasource}" },
      "fieldConfig": {
        "defaults": {
          "color": { "mode": "thresholds" },
          "thresholds": {
            "mode": "absolute",
            "steps": [
              { "color": "red", "value": null },
              { "color": "orange", "value": 0.99 },
              { "color": "yellow", "value": 0.995 },
              { "color": "green", "value": 0.999 }
            ]
          },
          "unit": "percentunit",
          "min": 0.95,
          "max": 1
        },
        "overrides": []
      },
      "gridPos": { "h": 6, "w": 8, "x": 0, "y": 1 },
      "id": 1,
      "options": {
        "minVizHeight": 75,
        "minVizWidth": 75,
        "orientation": "auto",
        "reduceOptions": { "calcs": ["lastNotNull"], "fields": "", "values": false },
        "showThresholdLabels": true,
        "showThresholdMarkers": true
      },
      "targets": [
        {
          "datasource": { "type": "prometheus", "uid": "${datasource}" },
          "expr": "avg(service:availability:ratio_1h{tier=\"1\"})",
          "legendFormat": "Tier 1 (Critical)",
          "refId": "A"
        }
      ],
      "title": "Tier 1 Availability (SLA: 99.9%)",
      "type": "gauge"
    },
    {
      "datasource": { "type": "prometheus", "uid": "${datasource}" },
      "fieldConfig": {
        "defaults": {
          "color": { "mode": "thresholds" },
          "thresholds": {
            "mode": "absolute",
            "steps": [
              { "color": "red", "value": null },
              { "color": "orange", "value": 0.98 },
              { "color": "yellow", "value": 0.99 },
              { "color": "green", "value": 0.995 }
            ]
          },
          "unit": "percentunit",
          "min": 0.95,
          "max": 1
        },
        "overrides": []
      },
      "gridPos": { "h": 6, "w": 8, "x": 8, "y": 1 },
      "id": 2,
      "options": {
        "minVizHeight": 75,
        "minVizWidth": 75,
        "orientation": "auto",
        "reduceOptions": { "calcs": ["lastNotNull"], "fields": "", "values": false },
        "showThresholdLabels": true,
        "showThresholdMarkers": true
      },
      "targets": [
        {
          "datasource": { "type": "prometheus", "uid": "${datasource}" },
          "expr": "avg(service:availability:ratio_1h{tier=\"2\"})",
          "legendFormat": "Tier 2 (Essential)",
          "refId": "A"
        }
      ],
      "title": "Tier 2 Availability (SLA: 99.5%)",
      "type": "gauge"
    },
    {
      "datasource": { "type": "prometheus", "uid": "${datasource}" },
      "fieldConfig": {
        "defaults": {
          "color": { "mode": "thresholds" },
          "thresholds": {
            "mode": "absolute",
            "steps": [
              { "color": "red", "value": null },
              { "color": "orange", "value": 0.97 },
              { "color": "yellow", "value": 0.98 },
              { "color": "green", "value": 0.99 }
            ]
          },
          "unit": "percentunit",
          "min": 0.95,
          "max": 1
        },
        "overrides": []
      },
      "gridPos": { "h": 6, "w": 8, "x": 16, "y": 1 },
      "id": 3,
      "options": {
        "minVizHeight": 75,
        "minVizWidth": 75,
        "orientation": "auto",
        "reduceOptions": { "calcs": ["lastNotNull"], "fields": "", "values": false },
        "showThresholdLabels": true,
        "showThresholdMarkers": true
      },
      "targets": [
        {
          "datasource": { "type": "prometheus", "uid": "${datasource}" },
          "expr": "avg(service:availability:ratio_1h{tier=~\"[3-9]\"})",
          "legendFormat": "Tier 3+ (Features)",
          "refId": "A"
        }
      ],
      "title": "Tier 3+ Availability (SLA: 99.0%)",
      "type": "gauge"
    },
    {
      "collapsed": false,
      "gridPos": { "h": 1, "w": 24, "x": 0, "y": 7 },
      "id": 101,
      "title": "Error Budget Remaining",
      "type": "row"
    },
    {
      "datasource": { "type": "prometheus", "uid": "${datasource}" },
      "fieldConfig": {
        "defaults": {
          "color": { "mode": "palette-classic" },
          "custom": {
            "axisBorderShow": false,
            "axisCenteredZero": false,
            "axisLabel": "budget remaining",
            "drawStyle": "line",
            "fillOpacity": 20,
            "lineInterpolation": "smooth",
            "lineWidth": 2,
            "pointSize": 5,
            "showPoints": "never",
            "spanNulls": false,
            "stacking": { "group": "A", "mode": "none" },
            "thresholdsStyle": { "mode": "line+area" }
          },
          "thresholds": {
            "mode": "absolute",
            "steps": [
              { "color": "red", "value": null },
              { "color": "transparent", "value": 0.10 },
              { "color": "transparent", "value": 0.25 }
            ]
          },
          "unit": "percentunit",
          "min": 0,
          "max": 1
        },
        "overrides": []
      },
      "gridPos": { "h": 8, "w": 24, "x": 0, "y": 8 },
      "id": 4,
      "options": {
        "legend": { "calcs": ["lastNotNull", "min"], "displayMode": "table", "placement": "right", "sortBy": "Last *", "sortDesc": false },
        "tooltip": { "mode": "multi", "sort": "asc" }
      },
      "targets": [
        {
          "datasource": { "type": "prometheus", "uid": "${datasource}" },
          "expr": "service:error_budget:remaining_30d",
          "legendFormat": "{{ service }} ({{ sla_target }}%)",
          "refId": "A"
        }
      ],
      "title": "Error Budget Remaining (30-Day Window)",
      "type": "timeseries"
    },
    {
      "collapsed": false,
      "gridPos": { "h": 1, "w": 24, "x": 0, "y": 16 },
      "id": 102,
      "title": "Latency P95 by Service",
      "type": "row"
    },
    {
      "datasource": { "type": "prometheus", "uid": "${datasource}" },
      "fieldConfig": {
        "defaults": {
          "color": { "mode": "palette-classic" },
          "custom": {
            "axisBorderShow": false,
            "axisCenteredZero": false,
            "axisLabel": "latency",
            "drawStyle": "line",
            "fillOpacity": 10,
            "lineInterpolation": "smooth",
            "lineWidth": 1,
            "pointSize": 5,
            "showPoints": "never",
            "spanNulls": false,
            "stacking": { "group": "A", "mode": "none" },
            "thresholdsStyle": { "mode": "line" }
          },
          "thresholds": {
            "mode": "absolute",
            "steps": [
              { "color": "green", "value": null },
              { "color": "yellow", "value": 0.5 },
              { "color": "red", "value": 2.0 }
            ]
          },
          "unit": "s"
        },
        "overrides": []
      },
      "gridPos": { "h": 8, "w": 12, "x": 0, "y": 17 },
      "id": 5,
      "options": {
        "legend": { "calcs": ["mean", "max"], "displayMode": "table", "placement": "bottom", "sortBy": "Max", "sortDesc": true },
        "tooltip": { "mode": "multi", "sort": "desc" }
      },
      "targets": [
        {
          "datasource": { "type": "prometheus", "uid": "${datasource}" },
          "expr": "service:latency:p95_5m{tier=\"1\"}",
          "legendFormat": "{{ service }} (Tier 1)",
          "refId": "A"
        },
        {
          "datasource": { "type": "prometheus", "uid": "${datasource}" },
          "expr": "service:latency:p95_5m{tier=\"2\"}",
          "legendFormat": "{{ service }} (Tier 2)",
          "refId": "B"
        }
      ],
      "title": "P95 Latency — Tier 1 & 2 Services",
      "type": "timeseries"
    },
    {
      "datasource": { "type": "prometheus", "uid": "${datasource}" },
      "fieldConfig": {
        "defaults": {
          "color": { "mode": "palette-classic" },
          "custom": {
            "axisBorderShow": false,
            "axisCenteredZero": false,
            "axisLabel": "latency",
            "drawStyle": "line",
            "fillOpacity": 10,
            "lineInterpolation": "smooth",
            "lineWidth": 1,
            "pointSize": 5,
            "showPoints": "never",
            "spanNulls": false,
            "stacking": { "group": "A", "mode": "none" },
            "thresholdsStyle": { "mode": "line" }
          },
          "thresholds": {
            "mode": "absolute",
            "steps": [
              { "color": "green", "value": null },
              { "color": "red", "value": 2.0 }
            ]
          },
          "unit": "s"
        },
        "overrides": []
      },
      "gridPos": { "h": 8, "w": 12, "x": 12, "y": 17 },
      "id": 6,
      "options": {
        "legend": { "calcs": ["mean", "max"], "displayMode": "table", "placement": "bottom", "sortBy": "Max", "sortDesc": true },
        "tooltip": { "mode": "multi", "sort": "desc" }
      },
      "targets": [
        {
          "datasource": { "type": "prometheus", "uid": "${datasource}" },
          "expr": "service:latency:p95_5m{tier=~\"[3-9]\"}",
          "legendFormat": "{{ service }} (Tier {{ tier }})",
          "refId": "A"
        }
      ],
      "title": "P95 Latency — Tier 3+ Services",
      "type": "timeseries"
    },
    {
      "collapsed": false,
      "gridPos": { "h": 1, "w": 24, "x": 0, "y": 25 },
      "id": 103,
      "title": "Active Alerts",
      "type": "row"
    },
    {
      "datasource": { "type": "prometheus", "uid": "${datasource}" },
      "fieldConfig": {
        "defaults": {
          "color": { "mode": "thresholds" },
          "custom": {
            "align": "auto",
            "cellOptions": { "type": "auto" },
            "filterable": true,
            "inspect": true
          },
          "thresholds": {
            "mode": "absolute",
            "steps": [
              { "color": "green", "value": null }
            ]
          }
        },
        "overrides": [
          {
            "matcher": { "id": "byName", "options": "severity" },
            "properties": [
              {
                "id": "custom.cellOptions",
                "value": {
                  "mode": "basic",
                  "type": "color-background"
                }
              },
              {
                "id": "mappings",
                "value": [
                  { "options": { "critical": { "color": "red", "index": 0, "text": "CRITICAL" } }, "type": "value" },
                  { "options": { "warning": { "color": "orange", "index": 1, "text": "WARNING" } }, "type": "value" }
                ]
              }
            ]
          }
        ]
      },
      "gridPos": { "h": 8, "w": 24, "x": 0, "y": 26 },
      "id": 7,
      "options": {
        "cellHeight": "sm",
        "footer": { "countRows": true, "enablePagination": true, "fields": "", "reducer": ["count"], "show": true },
        "showHeader": true,
        "sortBy": [{ "desc": true, "displayName": "severity" }]
      },
      "targets": [
        {
          "datasource": { "type": "prometheus", "uid": "${datasource}" },
          "expr": "ALERTS{alertstate=\"firing\"}",
          "format": "table",
          "instant": true,
          "legendFormat": "",
          "refId": "A"
        }
      ],
      "title": "Currently Firing Alerts",
      "transformations": [
        {
          "id": "organize",
          "options": {
            "excludeByName": { "Time": true, "Value": true, "__name__": true },
            "indexByName": {},
            "renameByName": {
              "alertname": "Alert",
              "alertstate": "State",
              "service": "Service",
              "severity": "Severity",
              "tier": "Tier",
              "group": "Group"
            }
          }
        }
      ],
      "type": "table"
    },
    {
      "collapsed": false,
      "gridPos": { "h": 1, "w": 24, "x": 0, "y": 34 },
      "id": 104,
      "title": "SLA Compliance History",
      "type": "row"
    },
    {
      "datasource": { "type": "prometheus", "uid": "${datasource}" },
      "fieldConfig": {
        "defaults": {
          "color": { "mode": "palette-classic" },
          "custom": {
            "axisBorderShow": false,
            "axisCenteredZero": false,
            "axisLabel": "availability",
            "drawStyle": "line",
            "fillOpacity": 5,
            "lineInterpolation": "smooth",
            "lineWidth": 2,
            "pointSize": 5,
            "showPoints": "never",
            "spanNulls": false,
            "stacking": { "group": "A", "mode": "none" },
            "thresholdsStyle": { "mode": "dashed+area" }
          },
          "thresholds": {
            "mode": "absolute",
            "steps": [
              { "color": "red", "value": null },
              { "color": "transparent", "value": 0.99 },
              { "color": "transparent", "value": 0.995 },
              { "color": "transparent", "value": 0.999 }
            ]
          },
          "unit": "percentunit",
          "min": 0.95,
          "max": 1
        },
        "overrides": []
      },
      "gridPos": { "h": 8, "w": 24, "x": 0, "y": 35 },
      "id": 8,
      "options": {
        "legend": { "calcs": ["mean", "min"], "displayMode": "table", "placement": "right", "sortBy": "Min", "sortDesc": false },
        "tooltip": { "mode": "multi", "sort": "asc" }
      },
      "targets": [
        {
          "datasource": { "type": "prometheus", "uid": "${datasource}" },
          "expr": "tier:availability:ratio_1h",
          "legendFormat": "Tier {{ tier }}",
          "refId": "A"
        }
      ],
      "title": "SLA Compliance History — Availability by Tier",
      "type": "timeseries"
    }
  ],
  "schemaVersion": 39,
  "tags": ["homeiq", "sla", "alerting", "epic-79"],
  "templating": {
    "list": [
      {
        "current": { "selected": false, "text": "Prometheus", "value": "prometheus" },
        "hide": 0,
        "includeAll": false,
        "label": "Data Source",
        "multi": false,
        "name": "datasource",
        "options": [],
        "query": "prometheus",
        "refresh": 1,
        "regex": "",
        "skipUrlSync": false,
        "type": "datasource"
      }
    ]
  },
  "time": { "from": "now-6h", "to": "now" },
  "timepicker": {},
  "timezone": "browser",
  "title": "HomeIQ SLA Overview",
  "uid": "homeiq-sla-overview",
  "version": 1
}
